[
  {
    "AirlineName": "Adria Airways",
    "CommissionName": "Eyaasttest",
    "GDSSupplier": "Galileo",
    "SupplierCredential": "Galileo Live UAE",
    "JourneyType": "One way",
    "TicketDesignator": "",
    "TourCode": "",
    "OriginAirport": "Anaa(AAA)",
    "DestinationAirport": "",
    "OriginCity": "",
    "DestinationCity": "",
    "OriginCountry": "",
    "DestinationCountry": "",
    "FareBasisCode": "",
    "ValidityPeriodFrom":"1",
    "ValidityPeriodTo": "15",
    "OutboundPeriodFrom": "",
    "OutboundPeriodTo": "",
    "InboundPeriodFrom": "",
    "InboundPeriodTo": "",
    "BlackoutInboundPeriodFrom": "",
    "BlackoutInboundPeriodTo": "",
    "BlackoutOutboundPeriodFrom": "",
    "BlackoutOutboundPeriodTo": "",
    "EnterValue": "10",
    "FareType": "Base Fare",
    "Amount": "Percentage",
    "A": "",
    "B": "",
    "C": "",
    "D": "",
    "E": "",
    "F": "",
    "G": "",
    "H": "",
    "I": "",
    "J": "",
    "K": "",
    "L": "",
    "M": "",
    "N": "",
    "O": "",
    "P": "",
    "Q": "",
    "R": "",
    "S": "",
    "U": "",
    "V": "",
    "W": "",
    "X": "",
    "Y": "",
    "Z": ""

  }
]